icodeuplay/__init__.py
icodeuplay/openai_client.py
tests/__init__.py
tests/test_openai_client.py
icodeuplay-0.0.1.dist-info/METADATA
icodeuplay-0.0.1.dist-info/WHEEL
icodeuplay-0.0.1.dist-info/top_level.txt
icodeuplay-0.0.1.dist-info/RECORD
