Metadata-Version: 2.1
Name: icodeuplay
Version: 0.0.1
Summary: Utilitary Python Library
Home-page: https://github.com/icodeuplay/icodeuplay
Author: Márcio Alves Barroso
Author-email: marciobarroso@gmail.com
Classifier: Programming Language :: Python :: 3
Classifier: License :: OSI Approved :: MIT License
Classifier: Operating System :: OS Independent
Requires-Python: >=3.6
Requires-Dist: python-dotenv
Requires-Dist: openai
Requires-Dist: openai-whisper
Requires-Dist: gtts
